raccoontools/__init__.py
raccoontools/decorators/__init__.py
raccoontools/decorators/benchmark.py
raccoontools/decorators/retry.py
raccoontools/generators/__init__.py
raccoontools/generators/file_ops_generators.py
raccoontools/generators/misc_generators.py
raccoontools/generators/sequence_generators.py
raccoontools/shared/__init__.py
raccoontools/shared/file_ops.py
raccoontools/shared/file_utils.py
raccoontools/shared/http.py
raccoontools/shared/requests_with_retry.py
raccoontools/shared/serializer.py
raccoontools-1.2.0.dist-info/METADATA
raccoontools-1.2.0.dist-info/WHEEL
raccoontools-1.2.0.dist-info/top_level.txt
raccoontools-1.2.0.dist-info/RECORD
