Metadata-Version: 2.4
Name: raccoontools
Version: 1.2.0
Summary: A collection of tools, and helpers that I usually want for a handful of projects, so to avoid rewriting them every time, I decided to create this package.
Home-page: https://github.com/brenordv/pypi-raccoon-tools
Author: Breno RdV
Author-email: Breno RdV <hello@raccoon.ninja>
Maintainer-email: Breno RdV <hello@raccoon.ninja>
License: MIT License
Project-URL: Homepage, https://github.com/brenordv/pypi-raccoon-tools
Project-URL: Source, https://github.com/brenordv/pypi-raccoon-tools
Project-URL: Bug Tracker, https://github.com/brenordv/pypi-raccoon-tools/issues
Project-URL: Changelog, https://github.com/brenordv/pypi-raccoon-tools/blob/master/changelog.md
Project-URL: Author, https://raccoon.ninja
Keywords: retry,decorator,benchmark,logging,requests,json,file operations,serialization,http,utilities,tools,helpers,python
Classifier: Development Status :: 4 - Beta
Classifier: Intended Audience :: Developers
Classifier: Intended Audience :: Information Technology
Classifier: Topic :: Software Development :: Libraries :: Python Modules
Classifier: Programming Language :: Python :: 3
Classifier: Programming Language :: Python :: 3.9
Classifier: Programming Language :: Python :: 3.10
Classifier: Programming Language :: Python :: 3.11
Classifier: License :: OSI Approved :: MIT License
Classifier: Operating System :: OS Independent
Requires-Python: >=3.9
Requires-Dist: raccoon-simple-stopwatch==0.0.3
Requires-Dist: simple-log-factory==0.0.1
Requires-Dist: requests>=2.32.5
Requires-Dist: pydantic>=2.12.4
Requires-Dist: typing-extensions==4.15.0
Dynamic: author
Dynamic: home-page
Dynamic: requires-python
